structurizr/__init__.py
structurizr/_version.py
structurizr/abstract_base.py
structurizr/base_model.py
structurizr/helpers.py
structurizr/workspace.py
structurizr/api/__init__.py
structurizr/api/api_response.py
structurizr/api/structurizr_client.py
structurizr/api/structurizr_client_exception.py
structurizr/api/structurizr_client_settings.py
structurizr/mixin/__init__.py
structurizr/mixin/childless_mixin.py
structurizr/mixin/model_ref_mixin.py
structurizr/mixin/viewset_ref_mixin.py
structurizr/model/__init__.py
structurizr/model/code_element.py
structurizr/model/code_element_role.py
structurizr/model/component.py
structurizr/model/container.py
structurizr/model/container_instance.py
structurizr/model/deployment_element.py
structurizr/model/deployment_node.py
structurizr/model/element.py
structurizr/model/enterprise.py
structurizr/model/groupable_element.py
structurizr/model/http_health_check.py
structurizr/model/implied_relationship_strategies.py
structurizr/model/infrastructure_node.py
structurizr/model/interaction_style.py
structurizr/model/location.py
structurizr/model/model.py
structurizr/model/model_item.py
structurizr/model/person.py
structurizr/model/perspective.py
structurizr/model/relationship.py
structurizr/model/sequential_integer_id_generator.py
structurizr/model/software_system.py
structurizr/model/software_system_instance.py
structurizr/model/static_structure_element.py
structurizr/model/static_structure_element_instance.py
structurizr/model/tags.py
structurizr/view/__init__.py
structurizr/view/abstract_view.py
structurizr/view/animation.py
structurizr/view/automatic_layout.py
structurizr/view/border.py
structurizr/view/branding.py
structurizr/view/color.py
structurizr/view/component_view.py
structurizr/view/configuration.py
structurizr/view/container_view.py
structurizr/view/deployment_view.py
structurizr/view/dynamic_view.py
structurizr/view/element_style.py
structurizr/view/element_view.py
structurizr/view/filtered_view.py
structurizr/view/font.py
structurizr_python-0.6.0.dist-info/LICENSE
structurizr_python-0.6.0.dist-info/METADATA
structurizr_python-0.6.0.dist-info/WHEEL
structurizr_python-0.6.0.dist-info/top_level.txt
structurizr_python-0.6.0.dist-info/zip-safe
structurizr_python-0.6.0.dist-info/RECORD
