Metadata-Version: 2.1
Name: structurizr-python
Version: 0.6.0
Summary: A Python client package for the Structurizr cloud service and on-premises installation.
Home-page: https://github.com/Midnighter/structurizr-python
Author: Moritz E. Beber
Author-email: midnighter@posteo.net
License: Apache-2.0
Download-URL: https://pypi.org/project/structurizr-python/
Project-URL: Source Code, https://github.com/Midnighter/structurizr-python
Project-URL: Documentation, https://structurizr-python.readthedocs.io
Project-URL: Bug Tracker, https://github.com/Midnighter/structurizr-python/issues
Keywords: Structurizr,Structurizr-API,C4 model,software architecture,diagrams-as-code,diagrams
Platform: UNKNOWN
Classifier: Development Status :: 3 - Alpha
Classifier: Environment :: Web Environment
Classifier: Intended Audience :: Developers
Classifier: Intended Audience :: Information Technology
Classifier: License :: OSI Approved :: Apache Software License
Classifier: Natural Language :: English
Classifier: Operating System :: OS Independent
Classifier: Programming Language :: Python :: 3.6
Classifier: Programming Language :: Python :: 3.7
Classifier: Programming Language :: Python :: 3.8
Classifier: Programming Language :: Python :: 3.9
Classifier: Programming Language :: Python :: 3 :: Only
Classifier: Topic :: Software Development :: Documentation
Requires-Python: >=3.6
License-File: LICENSE
Requires-Dist: depinfo
Requires-Dist: httpx (~=0.16)
Requires-Dist: ordered-set
Requires-Dist: pydantic (>=1.7.1)
Requires-Dist: python-dotenv
Requires-Dist: importlib-metadata ; python_version < "3.8"
Provides-Extra: development
Requires-Dist: black ; extra == 'development'
Requires-Dist: isort ; extra == 'development'
Requires-Dist: pep517 ; extra == 'development'
Requires-Dist: tox ; extra == 'development'
